pyrml/__init__.py
pyrml/functions.py
pyrml/grammar.lark
pyrml/pyrml_api.py
pyrml/pyrml_core.py
pyrml/pyrml_mapper.py
pyrml/pyrml_rdflib.py
pyrml/rml_vocab.py
pyrml_lib-0.6.0.dist-info/LICENSE
pyrml_lib-0.6.0.dist-info/METADATA
pyrml_lib-0.6.0.dist-info/WHEEL
pyrml_lib-0.6.0.dist-info/top_level.txt
pyrml_lib-0.6.0.dist-info/RECORD
