Metadata-Version: 2.2
Name: pyrml-lib
Version: 0.6.0
License-File: LICENSE
Requires-Dist: lark-parser<=0.12.0,>=0.12.0
Requires-Dist: pandas<=2.1.4,>=2.1.4
Requires-Dist: Jinja2<=3.1.2,>=3.1.2
Requires-Dist: rdflib<=7.1.3,>=7.1.3
Requires-Dist: SPARQLWrapper<=2.0.0,>=2.0.0
Requires-Dist: Flask<=2.2.2,>=2.2.2
Requires-Dist: jsonpath-ng<=1.5.3,>=1.5.3
Requires-Dist: shortuuid<=1.0.9,>=1.0.9
Requires-Dist: numpy<=1.26.4,>=1.26.4
Requires-Dist: python-slugify[unidecode]<=7.0.0,>=7.0.0
Requires-Dist: lxml<=5.1.0,>=5.1.0
Requires-Dist: SQLAlchemy<=1.4.46,>=1.4.46
Dynamic: requires-dist
